PDFU/PDFU_extract.py
PDFU/__init__.py
PDFU/command_line.py
PDFU-0.3.0.dist-info/LICENSE
PDFU-0.3.0.dist-info/METADATA
PDFU-0.3.0.dist-info/WHEEL
PDFU-0.3.0.dist-info/entry_points.txt
PDFU-0.3.0.dist-info/top_level.txt
PDFU-0.3.0.dist-info/RECORD
