Metadata-Version: 2.1
Name: PDFU
Version: 0.3.0
Summary: PDF Unembedder for PDFPage objects
Home-page: https://github.com/YM162/PDFU
Author: YM162
Author-email: david.fontaneda@estudiante.uam.es
Project-URL: Bug Tracker, https://github.com/YM162/PDFU/issues
Classifier: Programming Language :: Python :: 3
Classifier: License :: OSI Approved :: MIT License
Classifier: Operating System :: OS Independent
Requires-Python: >=3.6
License-File: LICENSE
Requires-Dist: pdfrw (>=0.4)
Requires-Dist: pikepdf (>=5.1.2)
Requires-Dist: pdfminer.six (>=20220524)
